st2auth_keystone_backend/__init__.py
st2auth_keystone_backend/keystone.py
tests/__init__.py
tests/unit/__init__.py
tests/unit/test_keystone_backend.py
st2_auth_backend_keystone-0.3.0.dist-info/LICENSE
st2_auth_backend_keystone-0.3.0.dist-info/METADATA
st2_auth_backend_keystone-0.3.0.dist-info/WHEEL
st2_auth_backend_keystone-0.3.0.dist-info/entry_points.txt
st2_auth_backend_keystone-0.3.0.dist-info/top_level.txt
st2_auth_backend_keystone-0.3.0.dist-info/RECORD
