Metadata-Version: 2.1
Name: st2-auth-backend-keystone
Version: 0.3.0
Summary: StackStorm authentication backend which reads credentials from an OpenStack Keystone instance.
Home-page: https://github.com/StackStorm/st2-auth-backend-keystone
Author: StackStorm, Inc.
Author-email: info@stackstorm.com
License: Apache License (2.0)
Download-URL: https://github.com/StackStorm/st2-auth-backend-keystone/tarball/master
Platform: Any
Classifier: Development Status :: 3 - Alpha
Classifier: License :: OSI Approved :: Apache Software License
Classifier: Programming Language :: Python
Classifier: Programming Language :: Python :: 3
Classifier: Programming Language :: Python :: 3.8
Classifier: Programming Language :: Python :: 3.9
Classifier: Programming Language :: Python :: 3.10
Classifier: Programming Language :: Python :: 3.11
Classifier: Intended Audience :: Developers
Classifier: Environment :: Console
Provides: st2auth_keystone_backend
Requires-Python: >=3.8
Requires-Dist: requests
